pybuilder_docstr_coverage/__init__.py
pybuilder_docstr_coverage-0.1.1.dist-info/METADATA
pybuilder_docstr_coverage-0.1.1.dist-info/WHEEL
pybuilder_docstr_coverage-0.1.1.dist-info/namespace_packages.txt
pybuilder_docstr_coverage-0.1.1.dist-info/top_level.txt
pybuilder_docstr_coverage-0.1.1.dist-info/zip-safe
pybuilder_docstr_coverage-0.1.1.dist-info/RECORD
