Metadata-Version: 2.1
Name: pybuilder-docstr-coverage
Version: 0.1.1
Summary: PyBuilder plugin that checks documentation coverage using docstr-coverage
Home-page: https://github.com/chylek/pybuilder-docstr-coverage
Author: Adam Chýlek
Author-email: adam.chylek@amitia-ai.com
Maintainer: 
Maintainer-email: 
License: MIT
Classifier: Development Status :: 3 - Alpha
Classifier: License :: OSI Approved :: MIT License
Classifier: Programming Language :: Python :: 3
